<Data>
  <CreatureType Name="Imp">
    <LevelRange>8,18</LevelRange>
    <Scale>0.9</Scale>
    <Attack>11</Attack>
    <Defence>13</Defence>
    <Armour>14</Armour>
    <Health>13</Health>
    <Stamina>19</Stamina>
    <Frequency>4</Frequency>
    <Interact/>
    <Desc>A vicious demonic imp</Desc>
    <Weapons>
      <Weapon Weight="1">Fire Bolt</Weapon>
    </Weapons>
    <Resistances>
      <Resistance Type="Fire" Value="50"/>
    </Resistances>
    <Tex Size="2">3,1</Tex>
  </CreatureType>
  <CreatureType Name="Demon Spawn">
    <Size>1</Size>
    <LevelRange>9,19</LevelRange>
    <Attack>14</Attack>
    <Defence>14</Defence>
    <Armour>20</Armour>
    <Health>18</Health>
    <Stamina>20</Stamina>
    <Frequency>2</Frequency>
    <Interact/>
    <Desc>A demonic servant with sharp claws</Desc>
    <Weapons>
      <Weapon Weight="1">Barbed Claws</Weapon>
    </Weapons>
    <Resistances>
      <Resistance Type="Fire" Value="50"/>
    </Resistances>
    <Scavenge>
      <Item Amount="0.1">Demon Blood</Item>
    </Scavenge>
    <Tex Size="2">1,1</Tex>
  </CreatureType>
  <CreatureType Name="Demon Clawbeast">
    <Size>1</Size>
    <LevelRange>10,20</LevelRange>
    <Attack>17</Attack>
    <Defence>15</Defence>
    <Armour>21</Armour>
    <Health>20</Health>
    <Stamina>20</Stamina>
    <Frequency>2</Frequency>
    <Interact/>
    <Desc>A demonic servant with sharp claws</Desc>
    <Weapons>
      <Weapon Weight="1">Barbed Claws</Weapon>
    </Weapons>
    <Resistances>
      <Resistance Type="Fire" Value="30"/>
    </Resistances>
    <Scavenge>
      <Item Amount="0.15">Demon Blood</Item>
    </Scavenge>
    <Tex Size="2">3,3</Tex>
  </CreatureType>
  <CreatureType Name="Lava Beast">
    <LevelRange>9,19</LevelRange>
    <Attack>16</Attack>
    <Defence>12</Defence>
    <Armour>17</Armour>
    <Health>13</Health>
    <Stamina>22</Stamina>
    <Frequency>2</Frequency>
    <Desc>A quadripedal demon that explodes in a burst of fire when killed.</Desc>
    <Weapons>
      <Weapon Weight="1">Claws</Weapon>
    </Weapons>
    <Resistances>
      <Resistance Type="Fire" Value="80"/>
    </Resistances>
    <Scavenge>
      <Item Amount="0.1">Demon Blood</Item>
      <Item Amount="0.15">Incendiary Bulb</Item>
    </Scavenge>
    <OnDeathEffect Name="BloodBurst">
      <Radius>1.5</Radius>
      <Effect>
        <Damage Type="Fire">7</Damage>
      </Effect>
      <Effect Name="Fire Damage">
        <Duration>2</Duration>
        <Damage Type="Fire">4</Damage>
      </Effect>
      <Sound>WetSplat</Sound>
    </OnDeathEffect>
    <Tex Size="2">1,3</Tex>
  </CreatureType>
  <CreatureType Name="Demon Swordmaster">
    <Size>2</Size>
    <Scale>1.7</Scale>
    <LevelRange>9,19</LevelRange>
    <Attack>22</Attack>
    <Defence>16</Defence>
    <Armour>22</Armour>
    <Health>26</Health>
    <Stamina>21</Stamina>
    <Interact/>
    <Desc>A large bipedal, horned demon with a huge fiery blade</Desc>
    <Weapons>
      <Weapon Weight="1">Demon Sword</Weapon>
    </Weapons>
    <Resistances>
      <Resistance Type="Fire" Value="100"/>
    </Resistances>
    <Scavenge>
      <Item Amount="1">Demon Blood</Item>
    </Scavenge>
    <Tex Size="4">5,1</Tex>
  </CreatureType>
  <CreatureType Name="Demon Lord">
    <Size>2</Size>
    <Scale>2.3</Scale>
    <LevelRange>10,20</LevelRange>
    <Attack>28</Attack>
    <Defence>17</Defence>
    <Armour>28</Armour>
    <Health>62</Health>
    <Stamina>24</Stamina>
    <Interact/>
    <Desc>A huge fiery demon lord with a giant sword and wings of fire.</Desc>
    <Boss/>
    <Weapons>
      <Weapon Weight="1">Demon Sword</Weapon>
    </Weapons>
    <Resistances>
      <Resistance Type="Fire" Value="100"/>
    </Resistances>
    <Scavenge>
      <Item Amount="3">Demon Blood</Item>
    </Scavenge>
    <Boss/>
    <Tex Size="4">5,5</Tex>
  </CreatureType>
</Data>

